hiinsta/InstagramMessenger.py
hiinsta/__init__.py
hiinsta/types/__init__.py
hiinsta/types/exeptions/InstagramApiExeption.py
hiinsta/types/exeptions/__init__.py
hiinsta-0.3.0.dist-info/licenses/LICENSE
tests/__init__.py
tests/test_core.py
tests/test_instagram_messenger.py
hiinsta-0.3.0.dist-info/METADATA
hiinsta-0.3.0.dist-info/WHEEL
hiinsta-0.3.0.dist-info/top_level.txt
hiinsta-0.3.0.dist-info/RECORD
